LICENSE
README.md
setup.py
MilkyWay.egg-info/PKG-INFO
MilkyWay.egg-info/SOURCES.txt
MilkyWay.egg-info/dependency_links.txt
MilkyWay.egg-info/requires.txt
MilkyWay.egg-info/top_level.txt
milkyway/__init__.py
milkyway/example.py
milkyway/trajectory.py
milkyway/waypoint.py
milkyway/splines/__init__.py
milkyway/splines/flexible_spline.py