Metadata-Version: 2.1
Name: MilkyWay
Version: 1.2.1
Summary: 2D Robot trajectory generation
Home-page: UNKNOWN
Author: Hali Lev Ari
Author-email: LevAri.Hali@gmail.com
License: UNKNOWN
Platform: UNKNOWN
License-File: LICENSE
